argilla_haystack/__init__.py
argilla_haystack/base.py
argilla_haystack/helpers.py
argilla_haystack-0.0.2.dist-info/METADATA
argilla_haystack-0.0.2.dist-info/WHEEL
argilla_haystack-0.0.2.dist-info/licenses/LICENSE
argilla_haystack-0.0.2.dist-info/licenses/LICENSE_HEADER
argilla_haystack-0.0.2.dist-info/RECORD
